pymelo/__init__.py
pymelo-0.0.2.dist-info/LICENSE
pymelo-0.0.2.dist-info/METADATA
pymelo-0.0.2.dist-info/WHEEL
pymelo-0.0.2.dist-info/top_level.txt
pymelo-0.0.2.dist-info/RECORD
