Metadata-Version: 2.1
Name: pymelo
Version: 0.0.2
Summary: Wrapper for DiscordPomeloAPI
Home-page: https://github.com/Nemupy/pymelo
Author: Nemupy
Author-email: nemu.otoyume@gmail.com
License-File: LICENSE
